postgresql_lock/__init__.py
postgresql_lock/asyncpg.py
postgresql_lock/errors.py
postgresql_lock/lock.py
postgresql_lock/psycopg2.py
postgresql_lock/psycopg3.py
postgresql_lock/py.typed
postgresql_lock/sqlalchemy.py
postgresql_lock-0.2.2.dist-info/LICENSE
postgresql_lock-0.2.2.dist-info/METADATA
postgresql_lock-0.2.2.dist-info/WHEEL
postgresql_lock-0.2.2.dist-info/RECORD
