Metadata-Version: 2.3
Name: postgresql-lock
Version: 0.2.2
Summary: Lock mechanism implemented with PostgreSQL advisory locks.
License: BSD-3-Clause
Keywords: postgresql,postgres,distributed,lock
Author: Sean Kerr
Author-email: sean@code-box.org
Requires-Python: >=3.7,<4.0
Classifier: License :: OSI Approved :: BSD License
Classifier: Programming Language :: Python :: 3
Classifier: Programming Language :: Python :: 3.7
Classifier: Programming Language :: Python :: 3.8
Classifier: Programming Language :: Python :: 3.9
Classifier: Programming Language :: Python :: 3.10
Classifier: Programming Language :: Python :: 3.11
Classifier: Programming Language :: Python :: 3.12
Classifier: Programming Language :: Python :: 3.13
Project-URL: Repository, https://github.com/seankerr/py-postgresql-lock
